slacksdk/__init__.py
slacksdk/verify.py
slacksdk-0.0.1a0.dist-info/LICENSE
slacksdk-0.0.1a0.dist-info/METADATA
slacksdk-0.0.1a0.dist-info/WHEEL
slacksdk-0.0.1a0.dist-info/top_level.txt
slacksdk-0.0.1a0.dist-info/RECORD
