Metadata-Version: 2.1
Name: slacksdk
Version: 0.0.1a0
Summary: A minimal slack sdk
Home-page: https://github.com/thanakritju/python-slack-events-sdk
Author: Thanakrit Juthamongkhon
Author-email: thanakrit.ju.work@gmail.com
License: UNKNOWN
Platform: UNKNOWN
Classifier: Programming Language :: Python :: 3
Classifier: License :: OSI Approved :: MIT License
Classifier: Operating System :: OS Independent
